{
    "authors": [
        "Ousseynou Wade"
    ],
    "date_download": "2019-04-03 17:37:47+00:00",
    "date_modify": null,
    "date_publish": null,
    "description": "Un violent incendie s\\xe2\\x80\\x99est d\\xc3\\xa9clar\\xc3\\xa9 hier nuit vers 3 h du matin \\xc3\\xa0 Mbao dans un entrep\\xc3\\xb4t de mati\\xc3\\xa8res premi\\xc3\\xa8res de confection de m\\xc3\\xa8ches, au niveau de la zone Franche industrielle. Ainsi, les perte...",
    "filename": "https%3A%2F%2Fwww.leral.net%2FIncendie-de-la-zone-France-industrielle-4-milliards-de-Fcfa-partis-en-fumee_a246383.html.json",
    "image_url": "https://www.leral.net/photo/art/grande/32285800-30113812.jpg?v=1554311706",
    "language": null,
    "localpath": null,
    "source_domain": "www.leral.net",
    "text": "\\t\\t\\t\n\\t\\t\\t\\t Incendie de la Zone Franche industrielle: 4 milliards de FCfa partis en fum\\xc3\\xa9e\n\\t\\t\\t\n\\t\\t\n\\t\\t\n\\t\\t R\\xc3\\xa9dig\\xc3\\xa9 par leral.net le Mercredi 3 Avril 2019 \\xc3\\xa0 17:57 | | 0 commentaire(s)|\n\\t\\t\\t\n\\t\\t\n\\t\\t\n\\t\\t\\t\\t\n\\t\\t\\t\n\\t\\t\\t\n\\t\\t\\t\n\\t\\t\n\\t\n\\t\\t\n\\t\n\\t\n\\t\\t\\t\n\\t\\t\\t\\t\\t Un violent incendie s\\xe2\\x80\\x99est d\\xc3\\xa9clar\\xc3\\xa9 hier nuit vers 3 h du matin \\xc3\\xa0 Mbao dans un entrep\\xc3\\xb4t de mati\\xc3\\xa8res premi\\xc3\\xa8res de confection de m\\xc3\\xa8ches, au niveau de la zone Franche industrielle.\nAinsi, les pertes enregistr\\xc3\\xa9es sont tr\\xc3\\xa8s importantes. Et, le feu qui a longtemps tenu t\\xc3\\xaate aux efforts des sapeurs-pompiers, a pu \\xc3\\xaatre finalement ma\\xc3\\xaetris\\xc3\\xa9 dans le petit matin. Le bilan des sapeurs-pompiers, fait \\xc3\\xa9tat d\\xe2\\x80\\x99un mort par asphyxie et d\\xe2\\x80\\x99importants d\\xc3\\xa9g\\xc3\\xa2ts mat\\xc3\\xa9riels, estim\\xc3\\xa9s \\xc3\\xa0 4 milliards de FCfa.\nLeral\n\\t\\t\\t\\t\n\\t\\t\\t\n\\t\\t\\t\\t\n\\t\\t\\t\n\\t\\t\n\\t\\t\\t\n\\t\\t\\t\n\\t\\t\\t\n\\t\\t\\t\n\\t\\t\\t\n\\t\\t\n\\t\\t\n\\t\\t\n\\t\n\\t\\t\nAccueil \\t\\t\\t\nEnvoyer \\xc3\\xa0 un ami \\t\\t\\t\nPartager sur facebook\n\\t\\t\n\\t\\t\n\\t\\t\n\\t\\t\n\\t\n\\t\\t\n\\t\\t\n\\t\\t\n\\t\n\\t\\t\n\\t\\t\n\\t\\t\n\\t\\t\n\\t\\t\n\\t\\t\n\\t\n\\t\n\\t\nCliquez-ici pour regarder plus de videos\n\\t\\t\\t\\t\n\\t\n\\t\\t\n\\t\\t\n\\t\\t\n\\t\n\\t",
    "title": "4 milliards de FCfa partis en fum\\xc3\\xa9e",
    "title_page": null,
    "title_rss": null,
    "url": "https://www.leral.net/Incendie-de-la-zone-France-industrielle-4-milliards-de-Fcfa-partis-en-fumee_a246383.html"
}