{
    "authors": [],
    "date_download": "2019-04-01 14:00:20+00:00",
    "date_modify": null,
    "date_publish": null,
    "description": "Die ARD wird auch in den kommenden drei Jahren umfangreich von der Tour de France berichten. Die Vertr\\xc3\\xa4ge wurden mit der Amaury Sport Organisation verl\\xc3\\xa4ngert.",
    "filename": "http%3A%2F%2Fwww.digitalfernsehen.de%2FTour-de-France-2019-bis-2021-bei-der-ARD-in-Web-und-TV.176778.0.html.json",
    "image_url": "http://www.digitalfernsehen.de/uploads/tx_txavcontent/Sportschau_Logo_NEU_start_15.jpg",
    "language": "de",
    "localpath": null,
    "source_domain": "www.digitalfernsehen.de",
    "text": "Die ARD wird auch in den kommenden drei Jahren umfangreich von der Tour de France berichten. Die Vertr\\xc3\\xa4ge wurden mit der Amaury Sport Organisation verl\\xc3\\xa4ngert.\nBis 2021 wird die Tour de France weiter auf ARD, One und Sportschau.de zu sehen sein. In diesem Jahr wird es vom 6. bis 28. Juli 2019 eine t\\xc3\\xa4gliche Live-\\xc3\\x9cbertragung im Ersten geben. \\r",
    "title": "Tour de France 2019 bis 2021 bei der ARD in Web und TV",
    "title_page": null,
    "title_rss": null,
    "url": "http://www.digitalfernsehen.de/Tour-de-France-2019-bis-2021-bei-der-ARD-in-Web-und-TV.176778.0.html"
}